bl2_seed_reader/__init__.py
bl2_seed_reader/__main__.py
bl2_seed_reader/enums.py
bl2_seed_reader/gui.py
bl2_seed_reader/seed.py
bl2_seed_reader-0.2.1.dist-info/METADATA
bl2_seed_reader-0.2.1.dist-info/WHEEL
bl2_seed_reader-0.2.1.dist-info/top_level.txt
bl2_seed_reader-0.2.1.dist-info/RECORD
