Metadata-Version: 2.1
Name: bl2-seed-reader
Version: 0.2.1
Summary: Parser for seed files from the Loot Randomizer mod for Borderlands 2
Author-email: Zoey Mae <admin@barkshark.xyz>
License: CNPL 7+
Project-URL: Homepage, https://git.barkshark.xyz/barkshark/bl2-seed-reader
Project-URL: Bug Tracker, https://git.barkshark.xyz/barkshark/bl2-seed-reader/issues
Project-URL: Documentation, https://docs.barkshark.xyz/bl2-seed-reader
Project-URL: Source Code, https://git.barkshark.xyz/barkshark/bl2-seed-reader
Keywords: python,borderlands 2
Platform: any
Classifier: Development Status :: 4 - Beta
Classifier: Intended Audience :: Developers
Classifier: Operating System :: OS Independent
Classifier: Programming Language :: Python
Classifier: Programming Language :: Python :: 3.11
Classifier: Programming Language :: Python :: 3.12
Classifier: Topic :: Software Development :: Libraries :: Python Modules
Classifier: Typing :: Typed
Requires-Python: >=3.11
Requires-Dist: barkshark-lib >=0.1.4
Provides-Extra: dev
Requires-Dist: flake8 ==7.0.0 ; extra == 'dev'
Requires-Dist: mypy ==1.9.0 ; extra == 'dev'
Requires-Dist: pyinstaller ==6.8.0 ; extra == 'dev'
Provides-Extra: docs
Requires-Dist: furo ==2024.1.29 ; extra == 'docs'
Requires-Dist: sphinx ==7.2.6 ; extra == 'docs'
Requires-Dist: sphinx-external-toc ==1.0.1 ; extra == 'docs'
Provides-Extra: gui
Requires-Dist: pyside6 ==6.7.2 ; extra == 'gui'
